x_scanner_commons/__init__.py
x_scanner_commons/config/__init__.py
x_scanner_commons/config/base.py
x_scanner_commons/config/validators.py
x_scanner_commons/core/__init__.py
x_scanner_commons/core/exceptions/__init__.py
x_scanner_commons/core/exceptions/base.py
x_scanner_commons/core/logging/__init__.py
x_scanner_commons/core/logging/logger.py
x_scanner_commons/infrastructure/__init__.py
x_scanner_commons/infrastructure/cache/__init__.py
x_scanner_commons/infrastructure/cache/cache.py
x_scanner_commons/infrastructure/cache/docs/BEST_PRACTICES.md
x_scanner_commons/infrastructure/cache/docs/MIGRATION_GUIDE.md
x_scanner_commons/infrastructure/cache/docs/README.md
x_scanner_commons/infrastructure/cache/interface.py
x_scanner_commons/infrastructure/cache/layers/__init__.py
x_scanner_commons/infrastructure/cache/layers/memory_layer.py
x_scanner_commons/infrastructure/cache/layers/redis_layer.py
x_scanner_commons/infrastructure/database/__init__.py
x_scanner_commons/infrastructure/database/docs/BEST_PRACTICES.md
x_scanner_commons/infrastructure/database/docs/MIGRATION_GUIDE.md
x_scanner_commons/infrastructure/database/docs/README.md
x_scanner_commons/infrastructure/database/session.py
x_scanner_commons/infrastructure/database/utils.py
x_scanner_commons/infrastructure/logger/__init__.py
x_scanner_commons/infrastructure/logger/backends/__init__.py
x_scanner_commons/infrastructure/logger/backends/aliyun_sls.py
x_scanner_commons/infrastructure/logger/backends/console.py
x_scanner_commons/infrastructure/logger/backends/file.py
x_scanner_commons/infrastructure/logger/decorators.py
x_scanner_commons/infrastructure/logger/formatters.py
x_scanner_commons/infrastructure/logger/interface.py
x_scanner_commons/infrastructure/logger/logger.py
x_scanner_commons/infrastructure/logger/models.py
x_scanner_commons/infrastructure/vault/__init__.py
x_scanner_commons/infrastructure/vault/client.py
x_scanner_commons/infrastructure/vault/config.py
x_scanner_commons-0.1.1.dist-info/METADATA
x_scanner_commons-0.1.1.dist-info/WHEEL
x_scanner_commons-0.1.1.dist-info/licenses/LICENSE
x_scanner_commons-0.1.1.dist-info/RECORD
