Metadata-Version: 2.4
Name: x-scanner-commons
Version: 0.1.1
Summary: Common utilities for X-Scanner microservices
License: MIT
License-File: LICENSE
Author: X-Scanner Team
Requires-Python: >=3.11,<4.0
Classifier: License :: OSI Approved :: MIT License
Classifier: Programming Language :: Python :: 3
Classifier: Programming Language :: Python :: 3.11
Classifier: Programming Language :: Python :: 3.12
Classifier: Programming Language :: Python :: 3.13
Classifier: Programming Language :: Python :: 3.14
Provides-Extra: all
Provides-Extra: cache
Provides-Extra: database
Provides-Extra: vault
Requires-Dist: aiocache[redis] (>=0.12,<0.13) ; extra == "cache" or extra == "all"
Requires-Dist: alembic (>=1.13,<2.0) ; extra == "database" or extra == "all"
Requires-Dist: async-lru (>=2.0.5,<3.0.0)
Requires-Dist: asyncpg (>=0.29,<0.31) ; extra == "database" or extra == "all"
Requires-Dist: hiredis (>=2.2,<3.0) ; extra == "cache" or extra == "all"
Requires-Dist: hvac (>=2.0,<3.0) ; extra == "vault" or extra == "all"
Requires-Dist: mmh3 (>=5.0,<6.0) ; extra == "cache" or extra == "all"
Requires-Dist: pydantic (>=2.0,<3.0)
Requires-Dist: pydantic-settings (>=2.0,<3.0)
Requires-Dist: redis (>=5.0,<6.0) ; extra == "cache" or extra == "all"
Requires-Dist: sqlalchemy (>=2.0,<3.0) ; extra == "database" or extra == "all"
